RandAlgo/RandAlgo.py
RandAlgo/__init__.py
RandAlgo/__main__.py
RandAlgo-1.0.0.dist-info/METADATA
RandAlgo-1.0.0.dist-info/WHEEL
RandAlgo-1.0.0.dist-info/entry_points.txt
RandAlgo-1.0.0.dist-info/top_level.txt
RandAlgo-1.0.0.dist-info/RECORD
