Metadata-Version: 2.1
Name: RandAlgo
Version: 1.0.0
Summary: A package that displays random algorithm questions
Home-page: UNKNOWN
Author: Munachimso Ike
Author-email: ikemunachii@gmail.com
License: UNKNOWN
Platform: UNKNOWN
Classifier: Programming Language :: Python :: 3.8
Classifier: License :: OSI Approved :: MIT License
Classifier: Operating System :: OS Independent
Requires-Python: >= 3.6
Requires-Dist: requests
